[
    {
        "ekbName": "ФВЦН1-15Г",
        "tuName": [
            "ПЯ0.223.361ТУ"
        ],
        "manufacturerName": [
            "АО «НИИ «ФЕРРИТДОМЕН»"
        ]
    },
    {
        "ekbName": "ФВЦН1-24А",
        "tuName": [
            "бШ2.238.183ТУ"
        ],
        "manufacturerName": [
            "АО «НПП «ФАЗА»"
        ]
    },
    {
        "ekbName": "ФВЦН1-24Б",
        "tuName": [
            "бШ2.238.183ТУ"
        ],
        "manufacturerName": [
            "АО «НПП «ФАЗА»"
        ]
    },
    {
        "ekbName": "ФВЦН1-24В",
        "tuName": [
            "бШ2.238.183ТУ"
        ],
        "manufacturerName": [
            "АО «НПП «ФАЗА»"
        ]
    },
    {
        "ekbName": "ФВЦН1-24ВМ",
        "tuName": [
            "бШ2.238.183ТУ"
        ],
        "manufacturerName": [
            "АО «НПП «ФАЗА»"
        ]
    },
    {
        "ekbName": "ФВЦН1-24Г",
        "tuName": [
            "бШ2.238.183ТУ"
        ],
        "manufacturerName": [
            "АО «НПП «ФАЗА»"
        ]
    },
    {
        "ekbName": "ФВЦН1-25А",
        "tuName": [
            "бШ2.238.183ТУ"
        ],
        "manufacturerName": [
            "АО «НПП «ФАЗА»"
        ]
    },
    {
        "ekbName": "ФВЦН1-25Б",
        "tuName": [
            "бШ2.238.183ТУ"
        ],
        "manufacturerName": [
            "АО «НПП «ФАЗА»"
        ]
    },
    {
        "ekbName": "ФВЦН1-25В",
        "tuName": [
            "бШ2.238.183ТУ"
        ],
        "manufacturerName": [
            "АО «НПП «ФАЗА»"
        ]
    },
    {
        "ekbName": "ФВЦН1-25Г",
        "tuName": [
            "бШ2.238.183ТУ"
        ],
        "manufacturerName": [
            "АО «НПП «ФАЗА»"
        ]
    },
    {
        "ekbName": "ФВЦН1-25Д",
        "tuName": [
            "бШ2.238.183ТУ"
        ],
        "manufacturerName": [
            "АО «НПП «ФАЗА»"
        ]
    },
    {
        "ekbName": "ФВЦН1-25Е",
        "tuName": [
            "бШ2.238.183ТУ"
        ],
        "manufacturerName": [
            "АО «НПП «ФАЗА»"
        ]
    },
    {
        "ekbName": "ФВЦН1-26А",
        "tuName": [
            "бШ2.238.183ТУ"
        ],
        "manufacturerName": [
            "АО «НПП «ФАЗА»"
        ]
    },
    {
        "ekbName": "ФВЦН1-26Б",
        "tuName": [
            "бШ2.238.183ТУ"
        ],
        "manufacturerName": [
            "АО «НПП «ФАЗА»"
        ]
    },
    {
        "ekbName": "ФВЦН1-26В",
        "tuName": [
            "бШ2.238.183ТУ"
        ],
        "manufacturerName": [
            "АО «НПП «ФАЗА»"
        ]
    },
    {
        "ekbName": "ФВЦН1-26Г",
        "tuName": [
            "бШ2.238.183ТУ"
        ],
        "manufacturerName": [
            "АО «НПП «ФАЗА»"
        ]
    },
    {
        "ekbName": "ФВЦН1-26Д",
        "tuName": [
            "бШ2.238.183ТУ"
        ],
        "manufacturerName": [
            "АО «НПП «ФАЗА»"
        ]
    },
    {
        "ekbName": "ФВЦН1-26Е",
        "tuName": [
            "бШ2.238.183ТУ"
        ],
        "manufacturerName": [
            "АО «НПП «ФАЗА»"
        ]
    },
    {
        "ekbName": "ФВЦН1-27А",
        "tuName": [
            "бШ2.238.183ТУ"
        ],
        "manufacturerName": [
            "АО «НПП «ФАЗА»"
        ]
    },
    {
        "ekbName": "ФВЦН1-27Б",
        "tuName": [
            "бШ2.238.183ТУ"
        ],
        "manufacturerName": [
            "АО «НПП «ФАЗА»"
        ]
    },
    {
        "ekbName": "ФВЦН1-27В",
        "tuName": [
            "бШ2.238.183ТУ"
        ],
        "manufacturerName": [
            "АО «НПП «ФАЗА»"
        ]
    },
    {
        "ekbName": "ФВЦН1-27Г",
        "tuName": [
            "бШ2.238.183ТУ"
        ],
        "manufacturerName": [
            "АО «НПП «ФАЗА»"
        ]
    },
    {
        "ekbName": "ФВЦН1-27Д",
        "tuName": [
            "бШ2.238.183ТУ"
        ],
        "manufacturerName": [
            "АО «НПП «ФАЗА»"
        ]
    },
    {
        "ekbName": "ФВЦН1-27Е",
        "tuName": [
            "бШ2.238.183ТУ"
        ],
        "manufacturerName": [
            "АО «НПП «ФАЗА»"
        ]
    },
    {
        "ekbName": "ФВЦН1-27Ж",
        "tuName": [
            "бШ2.238.183ТУ"
        ],
        "manufacturerName": [
            "АО «НПП «ФАЗА»"
        ]
    },
    {
        "ekbName": "ФВЦН1-27З",
        "tuName": [
            "бШ2.238.183ТУ"
        ],
        "manufacturerName": [
            "АО «НПП «ФАЗА»"
        ]
    },
    {
        "ekbName": "ФВЦН1-28А",
        "tuName": [
            "бШ2.238.183ТУ"
        ],
        "manufacturerName": [
            "АО «НПП «ФАЗА»"
        ]
    },
    {
        "ekbName": "ФВЦН1-28Б",
        "tuName": [
            "бШ2.238.183ТУ"
        ],
        "manufacturerName": [
            "АО «НПП «ФАЗА»"
        ]
    },
    {
        "ekbName": "ФВЦН1-28В",
        "tuName": [
            "бШ2.238.183ТУ"
        ],
        "manufacturerName": [
            "АО «НПП «ФАЗА»"
        ]
    },
    {
        "ekbName": "ФВЦН1-28Г",
        "tuName": [
            "бШ2.238.183ТУ"
        ],
        "manufacturerName": [
            "АО «НПП «ФАЗА»"
        ]
    },
    {
        "ekbName": "ФВЦН1-28Д",
        "tuName": [
            "бШ2.238.183ТУ"
        ],
        "manufacturerName": [
            "АО «НПП «ФАЗА»"
        ]
    },
    {
        "ekbName": "ФВЦН1-28Е",
        "tuName": [
            "бШ2.238.183ТУ"
        ],
        "manufacturerName": [
            "АО «НПП «ФАЗА»"
        ]
    },
    {
        "ekbName": "ФВЦН1-28Ж",
        "tuName": [
            "бШ2.238.183ТУ"
        ],
        "manufacturerName": [
            "АО «НПП «ФАЗА»"
        ]
    },
    {
        "ekbName": "ФВЦН1-28З",
        "tuName": [
            "бШ2.238.183ТУ"
        ],
        "manufacturerName": [
            "АО «НПП «ФАЗА»"
        ]
    },
    {
        "ekbName": "ФВЦН1-28И",
        "tuName": [
            "бШ2.238.183ТУ"
        ],
        "manufacturerName": [
            "АО «НПП «ФАЗА»"
        ]
    },
    {
        "ekbName": "ФВЦН1-28К",
        "tuName": [
            "бШ2.238.183ТУ"
        ],
        "manufacturerName": [
            "АО «НПП «ФАЗА»"
        ]
    },
    {
        "ekbName": "ФВЦН1-39",
        "tuName": [
            "КЖГП.468540.013ТУ"
        ],
        "manufacturerName": [
            "АО «НИИ «ФЕРРИТДОМЕН»"
        ]
    },
    {
        "ekbName": "ФВЦН1-40",
        "tuName": [
            "КЖГП.468540.022ТУ"
        ],
        "manufacturerName": [
            "АО «НИИ «ФЕРРИТДОМЕН»"
        ]
    },
    {
        "ekbName": "ФВЦН1-41",
        "tuName": [
            "КЖГП.468540.027ТУ"
        ],
        "manufacturerName": [
            "АО «НИИ «ФЕРРИТДОМЕН»"
        ]
    },
    {
        "ekbName": "ФВЦН1-43",
        "tuName": [
            "КЖГП.468540.063ТУ"
        ],
        "manufacturerName": [
            "АО «НИИ «ФЕРРИТДОМЕН»"
        ]
    },
    {
        "ekbName": "ФВЦН1-43А",
        "tuName": [
            "КЖГП.468540.063ТУ"
        ],
        "manufacturerName": [
            "АО «НИИ «ФЕРРИТДОМЕН»"
        ]
    },
    {
        "ekbName": "ФВЦН2-25",
        "tuName": [
            "ПЯ0.223.373ТУ"
        ],
        "manufacturerName": [
            "АО «НИИ «ФЕРРИТДОМЕН»"
        ]
    },
    {
        "ekbName": "ФВЦН2-26",
        "tuName": [
            "ПЯ0.223.373ТУ"
        ],
        "manufacturerName": [
            "АО «НИИ «ФЕРРИТДОМЕН»"
        ]
    },
    {
        "ekbName": "ФВЦН2-29",
        "tuName": [
            "ПЯ0.223.410ТУ"
        ],
        "manufacturerName": [
            "АО «НИИ «ФЕРРИТДОМЕН»"
        ]
    },
    {
        "ekbName": "ФВЦН2-42",
        "tuName": [
            "КЖГП.468540.003ТУ"
        ],
        "manufacturerName": [
            "АО «НИИ «ФЕРРИТДОМЕН»"
        ]
    },
    {
        "ekbName": "ФВЦН2-43",
        "tuName": [
            "ПЯ0.223.177ТУ"
        ],
        "manufacturerName": [
            "АО «ФЕРРОПРИБОР»",
            "ОАО «ЗАВОД МАГНЕТОН»",
            "ООО «НПО «ЗАВОД «МАГНЕТОН»"
        ]
    },
    {
        "ekbName": "ФЦВ1-28А",
        "tuName": [
            "ПЯ0.223.177ТУ"
        ],
        "manufacturerName": [
            "АО «НИИ «ФЕРРИТДОМЕН»",
            "ОАО «ЗАВОД МАГНЕТОН»",
            "ООО «НПО «ЗАВОД «МАГНЕТОН»"
        ]
    },
    {
        "ekbName": "ФЦВ1-28Б",
        "tuName": [
            "ПЯ0.223.177ТУ"
        ],
        "manufacturerName": [
            "АО «НИИ «ФЕРРИТДОМЕН»",
            "ОАО «ЗАВОД МАГНЕТОН»",
            "ООО «НПО «ЗАВОД «МАГНЕТОН»"
        ]
    },
    {
        "ekbName": "ФЦВ1-29",
        "tuName": [
            "ПЯ0.223.177ТУ"
        ],
        "manufacturerName": [
            "АО «НИИ «ФЕРРИТДОМЕН»",
            "АО «ФЕРРОПРИБОР»",
            "ОАО «ЗАВОД МАГНЕТОН»",
            "ООО «НПО «ЗАВОД «МАГНЕТОН»"
        ]
    },
    {
        "ekbName": "ФЦВ2-44",
        "tuName": [
            "ПЯ0.223.177ТУ"
        ],
        "manufacturerName": [
            "АО «НИИ «ФЕРРИТДОМЕН»",
            "АО «ФЕРРОПРИБОР»",
            "ОАО «ЗАВОД МАГНЕТОН»",
            "ООО «НПО «ЗАВОД «МАГНЕТОН»"
        ]
    },
    {
        "ekbName": "ФЦВ2-45",
        "tuName": [
            "ПЯ0.223.177ТУ"
        ],
        "manufacturerName": [
            "АО «НИИ «ФЕРРИТДОМЕН»",
            "АО «ФЕРРОПРИБОР»",
            "ОАО «ЗАВОД МАГНЕТОН»",
            "ООО «НПО «ЗАВОД «МАГНЕТОН»"
        ]
    },
    {
        "ekbName": "ФЦВ2-46",
        "tuName": [
            "ПЯ0.223.177ТУ"
        ],
        "manufacturerName": [
            "АО «ФЕРРОПРИБОР»",
            "ОАО «ЗАВОД МАГНЕТОН»",
            "ООО «НПО «ЗАВОД «МАГНЕТОН»"
        ]
    },
    {
        "ekbName": "ФЦВ2-47",
        "tuName": [
            "ПЯ0.223.177ТУ"
        ],
        "manufacturerName": [
            "АО «ФЕРРОПРИБОР»",
            "ОАО «ЗАВОД МАГНЕТОН»",
            "ООО «НПО «ЗАВОД «МАГНЕТОН»"
        ]
    }
]