[
    {
        "Name": "2РМ-А1",
        "Parameters": {
            "11": [
                "1Е-3 - 700"
            ],
            "1100": [
                "1Е-4 - 36"
            ],
            "1101": [
                "4 - 50"
            ],
            "1102": [
                "14 - 42"
            ]
        }
    },
    {
        "Name": "2РМ-В1",
        "Parameters": {
            "11": [
                "1Е-3 - 700"
            ],
            "1100": [
                "1Е-4 - 36"
            ],
            "1101": [
                "4 - 50"
            ],
            "1102": [
                "14 - 42"
            ]
        }
    },
    {
        "Name": "2РМГС-С",
        "Parameters": {
            "11": [
                "700"
            ],
            "1100": [
                "5.75"
            ],
            "1101": [
                "10 - 50"
            ],
            "1102": [
                "22",
                " 27",
                " 42"
            ]
        }
    },
    {
        "Name": "2РМД-А1",
        "Parameters": {
            "11": [
                "1Е-3 - 700"
            ],
            "1100": [
                "1Е-4 - 36"
            ],
            "1101": [
                "7 - 50"
            ],
            "1102": [
                "18",
                " 24 - 45"
            ]
        }
    },
    {
        "Name": "2РМД-В1",
        "Parameters": {
            "11": [
                "1Е-3 - 700"
            ],
            "1100": [
                "1Е-4 - 36"
            ],
            "1101": [
                "4 - 50"
            ],
            "1102": [
                "18",
                " 24 - 45"
            ]
        }
    },
    {
        "Name": "ОНЦ-РГ-8",
        "Parameters": {
            "11": [
                "100"
            ],
            "1100": [
                "4"
            ],
            "1101": [
                "2"
            ],
            "1102": [
                "11"
            ]
        }
    },
    {
        "Name": "ОС 2РМ-А1",
        "Parameters": {
            "11": [
                "1Е-3 - 560"
            ],
            "1100": [
                "1Е-4 - 7",
                "  1Е-4 - 8"
            ],
            "1101": [
                "7",
                " 4"
            ],
            "1102": [
                "18",
                " 14"
            ]
        }
    },
    {
        "Name": "ОС 2РМ-В1",
        "Parameters": {
            "11": [
                "1Е-3 - 560"
            ],
            "1100": [
                "1Е-4 - 7",
                "  1Е-4 - 8"
            ],
            "1101": [
                "7",
                " 4"
            ],
            "1102": [
                "18",
                " 14"
            ]
        }
    },
    {
        "Name": "ОС 2РМГП",
        "Parameters": {
            "11": [
                "20Е-3 - 700"
            ],
            "1100": [
                "1Е-7 - 16"
            ],
            "1101": [
                "4 - 50"
            ],
            "1102": [
                "14 - 42"
            ]
        }
    },
    {
        "Name": "ОС 2РМГПД",
        "Parameters": {
            "11": [
                "20Е-3 - 700"
            ],
            "1100": [
                "1Е-7 - 18"
            ],
            "1101": [
                "4 - 45"
            ],
            "1102": [
                "18 - 42"
            ]
        }
    },
    {
        "Name": "ОС 2РМГС",
        "Parameters": {
            "11": [
                "20Е-3 - 700"
            ],
            "1100": [
                "1Е-7 - 7"
            ],
            "1101": [
                "10 - 50"
            ],
            "1102": [
                "22",
                " 27",
                " 42"
            ]
        }
    },
    {
        "Name": "ОС 2РМГСД",
        "Parameters": {
            "11": [
                "20Е-3 - 700"
            ],
            "1100": [
                "1Е-7 - 20"
            ],
            "1101": [
                "7 - 45"
            ],
            "1102": [
                "33",
                " 42"
            ]
        }
    },
    {
        "Name": "ОС 2РМГСПД",
        "Parameters": {
            "11": [
                "20Е-3 - 700"
            ],
            "1100": [
                "1Е-7 - 18"
            ],
            "1101": [
                "7 - 45"
            ],
            "1102": [
                "33",
                " 42"
            ]
        }
    },
    {
        "Name": "ОС 2РМД-А1",
        "Parameters": {
            "11": [
                "1Е-3 - 560"
            ],
            "1100": [
                "1Е-4 - 15"
            ],
            "1101": [
                "4"
            ],
            "1102": [
                "18"
            ]
        }
    },
    {
        "Name": "ОС 2РМД-В1",
        "Parameters": {
            "11": [
                "1Е-3 - 560"
            ],
            "1100": [
                "1Е-4 - 15"
            ],
            "1101": [
                "4"
            ],
            "1102": [
                "18"
            ]
        }
    },
    {
        "Name": "СГ-51",
        "Parameters": {
            "11": [
                "300",
                " 180"
            ],
            "1100": [
                "0.5",
                " 3",
                " 12",
                " 60"
            ],
            "1101": [
                "51"
            ],
            "1102": [
                "55"
            ]
        }
    },
    {
        "Name": "СГ-51НВ",
        "Parameters": {
            "11": [
                "300",
                " 180"
            ],
            "1100": [
                "0.5",
                " 3",
                " 12",
                " 60"
            ],
            "1101": [
                "51"
            ],
            "1102": [
                "55"
            ]
        }
    },
    {
        "Name": "СНЦ106",
        "Parameters": {
            "11": [
                "10Е-3 - 500"
            ],
            "1100": [
                "10Е-7 - 15"
            ],
            "1101": [
                "4 - 50"
            ]
        }
    },
    {
        "Name": "СНЦ107",
        "Parameters": {
            "11": [
                "10Е-3 - 500"
            ],
            "1100": [
                "10Е-7 - 15"
            ],
            "1101": [
                "4 - 50"
            ]
        }
    },
    {
        "Name": "СНЦ111",
        "Parameters": {
            "11": [
                "0.2 - 100"
            ],
            "1100": [
                "1Е-5 - 25"
            ],
            "1101": [
                "64"
            ],
            "1102": [
                "36"
            ]
        }
    }
]