[
    {
        "ekbName": "1491УД1АТ",
        "tuName": [
            "АЕЯР.431130.866-01ТУ"
        ],
        "manufacturerName": [
            "АО «ВОСХОД»- КРЛЗ"
        ]
    },
    {
        "ekbName": "1491УД1АТ1",
        "tuName": [
            "АЕЯР.431130.866-01ТУ"
        ],
        "manufacturerName": [
            "АО «ВОСХОД»- КРЛЗ"
        ]
    },
    {
        "ekbName": "1491УД1БТ",
        "tuName": [
            "АЕЯР.431130.866-01ТУ"
        ],
        "manufacturerName": [
            "АО «ВОСХОД»- КРЛЗ"
        ]
    },
    {
        "ekbName": "1491УД1БТ1",
        "tuName": [
            "АЕЯР.431130.866-01ТУ"
        ],
        "manufacturerName": [
            "АО «ВОСХОД»- КРЛЗ"
        ]
    },
    {
        "ekbName": "1491УД2АТ",
        "tuName": [
            "АЕЯР.431130.866-02ТУ"
        ],
        "manufacturerName": [
            "АО «ВОСХОД»- КРЛЗ"
        ]
    },
    {
        "ekbName": "1491УД2АТ1",
        "tuName": [
            "АЕЯР.431130.866-02ТУ"
        ],
        "manufacturerName": [
            "АО «ВОСХОД»- КРЛЗ"
        ]
    },
    {
        "ekbName": "1491УД2БТ",
        "tuName": [
            "АЕЯР.431130.866-02ТУ"
        ],
        "manufacturerName": [
            "АО «ВОСХОД»- КРЛЗ"
        ]
    },
    {
        "ekbName": "1491УД2БТ1",
        "tuName": [
            "АЕЯР.431130.866-02ТУ"
        ],
        "manufacturerName": [
            "АО «ВОСХОД»- КРЛЗ"
        ]
    }
]