[
    {
        "ekbName": "1526АГ1",
        "tuName": [
            "бК0.347.458-21ТУ"
        ],
        "manufacturerName": [
            "АО «ЭКСИТОН»"
        ]
    },
    {
        "ekbName": "1526ИД1",
        "tuName": [
            "бК0.347.458-05ТУ"
        ],
        "manufacturerName": [
            "АО «НЗПП ВОСТОК»"
        ]
    },
    {
        "ekbName": "1526ИД1 ММ",
        "tuName": [
            "АЕЯР.431200.139-05ТУ"
        ],
        "manufacturerName": [
            "АО «МИКРОН»"
        ]
    },
    {
        "ekbName": "1526ИД1 ЭП",
        "tuName": [
            "АЕЯР.431200.126-12ТУ"
        ],
        "manufacturerName": [
            "АО «ЭКСИТОН»"
        ]
    },
    {
        "ekbName": "1526ИЕ10",
        "tuName": [
            "бК0.347.458-13ТУ"
        ],
        "manufacturerName": [
            "АО «ЭКСИТОН»"
        ]
    },
    {
        "ekbName": "1526ИЕ10 ММ",
        "tuName": [
            "АЕЯР.431200.139-13ТУ"
        ],
        "manufacturerName": [
            "АО «МИКРОН»"
        ]
    },
    {
        "ekbName": "1526ИЕ11",
        "tuName": [
            "бК0.347.458-02ТУ"
        ],
        "manufacturerName": [
            "АО «НЗПП ВОСТОК»"
        ]
    },
    {
        "ekbName": "1526ИЕ11 ММ",
        "tuName": [
            "АЕЯР.431200.139-02ТУ"
        ],
        "manufacturerName": [
            "АО «МИКРОН»"
        ]
    },
    {
        "ekbName": "1526ИЕ11 ЭП",
        "tuName": [
            "АЕЯР.431200.126-02ТУ"
        ],
        "manufacturerName": [
            "АО «ЭКСИТОН»"
        ]
    },
    {
        "ekbName": "1526ИЕ14",
        "tuName": [
            "бК0.347.458-02ТУ"
        ],
        "manufacturerName": [
            "АО «НЗПП ВОСТОК»"
        ]
    },
    {
        "ekbName": "1526ИЕ14 ММ",
        "tuName": [
            "АЕЯР.431200.139-02ТУ"
        ],
        "manufacturerName": [
            "АО «МИКРОН»"
        ]
    },
    {
        "ekbName": "1526ИЕ14 ЭП",
        "tuName": [
            "АЕЯР.431200.126-02ТУ"
        ],
        "manufacturerName": [
            "АО «ЭКСИТОН»"
        ]
    },
    {
        "ekbName": "1526ИЕ15",
        "tuName": [
            "бК0.347.458-05ТУ"
        ],
        "manufacturerName": [
            "АО «НЗПП ВОСТОК»"
        ]
    },
    {
        "ekbName": "1526ИЕ15 ЭП",
        "tuName": [
            "АЕЯР.431200.126-11ТУ"
        ],
        "manufacturerName": [
            "АО «ЭКСИТОН»"
        ]
    },
    {
        "ekbName": "1526ИЕ19",
        "tuName": [
            "бК0.347.458-05ТУ"
        ],
        "manufacturerName": [
            "АО «НЗПП ВОСТОК»"
        ]
    },
    {
        "ekbName": "1526ИЕ19 ЭП",
        "tuName": [
            "АЕЯР.431200.126-11ТУ"
        ],
        "manufacturerName": [
            "АО «ЭКСИТОН»"
        ]
    },
    {
        "ekbName": "1526ИЕ9",
        "tuName": [
            "бК0.347.458-12ТУ"
        ],
        "manufacturerName": [
            "АО «ЭКСИТОН»"
        ]
    },
    {
        "ekbName": "1526ИК1",
        "tuName": [
            "бК0.347.458-05ТУ"
        ],
        "manufacturerName": [
            "АО «НЗПП ВОСТОК»"
        ]
    },
    {
        "ekbName": "1526ИК1 ММ",
        "tuName": [
            "АЕЯР.431200.139-05ТУ"
        ],
        "manufacturerName": [
            "АО «МИКРОН»"
        ]
    },
    {
        "ekbName": "1526ИК1 ЭП",
        "tuName": [
            "АЕЯР.431200.126-13ТУ"
        ],
        "manufacturerName": [
            "АО «ЭКСИТОН»"
        ]
    },
    {
        "ekbName": "1526ИМ1",
        "tuName": [
            "бК0.347.458-03ТУ"
        ],
        "manufacturerName": [
            "АО «НЗПП ВОСТОК»"
        ]
    },
    {
        "ekbName": "1526ИМ1 ММ",
        "tuName": [
            "АЕЯР.431200.139-03ТУ"
        ],
        "manufacturerName": [
            "АО «МИКРОН»"
        ]
    },
    {
        "ekbName": "1526ИМ1 ЭП",
        "tuName": [
            "АЕЯР.431200.126-03ТУ"
        ],
        "manufacturerName": [
            "АО «ЭКСИТОН»"
        ]
    },
    {
        "ekbName": "1526ИП2",
        "tuName": [
            "бК0.347.458-13ТУ"
        ],
        "manufacturerName": [
            "АО «ЭКСИТОН»"
        ]
    },
    {
        "ekbName": "1526ИП2 ММ",
        "tuName": [
            "АЕЯР.431200.139-13ТУ"
        ],
        "manufacturerName": [
            "АО «МИКРОН»"
        ]
    },
    {
        "ekbName": "1526ИП3",
        "tuName": [
            "бК0.347.458-05ТУ"
        ],
        "manufacturerName": [
            "АО «НЗПП ВОСТОК»"
        ]
    },
    {
        "ekbName": "1526ИП3 ММ",
        "tuName": [
            "АЕЯР.431200.139-05ТУ"
        ],
        "manufacturerName": [
            "АО «МИКРОН»"
        ]
    },
    {
        "ekbName": "1526ИП3 ЭП",
        "tuName": [
            "АЕЯР.431200.126-09ТУ"
        ],
        "manufacturerName": [
            "АО «ЭКСИТОН»"
        ]
    },
    {
        "ekbName": "1526ИП4",
        "tuName": [
            "бК0.347.458-05ТУ"
        ],
        "manufacturerName": [
            "АО «НЗПП ВОСТОК»"
        ]
    },
    {
        "ekbName": "1526ИП4 ММ",
        "tuName": [
            "АЕЯР.431200.139-05ТУ"
        ],
        "manufacturerName": [
            "АО «МИКРОН»"
        ]
    },
    {
        "ekbName": "1526ИП4 ЭП",
        "tuName": [
            "АЕЯР.431200.126-09ТУ"
        ],
        "manufacturerName": [
            "АО «ЭКСИТОН»"
        ]
    },
    {
        "ekbName": "1526ИП5 ЭП",
        "tuName": [
            "АЕЯР.431200.126-04ТУ"
        ],
        "manufacturerName": [
            "АО «ЭКСИТОН»"
        ]
    },
    {
        "ekbName": "1526ИП6",
        "tuName": [
            "бК0.347.458-05ТУ"
        ],
        "manufacturerName": [
            "АО «НЗПП ВОСТОК»"
        ]
    },
    {
        "ekbName": "1526ИП6 ММ",
        "tuName": [
            "АЕЯР.431200.139-05ТУ"
        ],
        "manufacturerName": [
            "АО «МИКРОН»"
        ]
    },
    {
        "ekbName": "1526ИП6 ЭП",
        "tuName": [
            "АЕЯР.431200.126-10ТУ"
        ],
        "manufacturerName": [
            "АО «ЭКСИТОН»"
        ]
    },
    {
        "ekbName": "1526ИР1",
        "tuName": [
            "бК0.347.458-10ТУ"
        ],
        "manufacturerName": [
            "АО «ЭКСИТОН»"
        ]
    },
    {
        "ekbName": "1526ИР1 ММ",
        "tuName": [
            "АЕЯР.431200.139-10ТУ"
        ],
        "manufacturerName": [
            "АО «МИКРОН»"
        ]
    },
    {
        "ekbName": "1526ИР11",
        "tuName": [
            "бК0.347.458-14ТУ"
        ],
        "manufacturerName": [
            "АО «ЭКСИТОН»"
        ]
    },
    {
        "ekbName": "1526ИР11 ММ",
        "tuName": [
            "АЕЯР.431200.139-14ТУ"
        ],
        "manufacturerName": [
            "АО «МИКРОН»"
        ]
    },
    {
        "ekbName": "1526ИР12 ЭП",
        "tuName": [
            "АЕЯР.431200.126-05ТУ"
        ],
        "manufacturerName": [
            "АО «ЭКСИТОН»"
        ]
    },
    {
        "ekbName": "1526ИР13",
        "tuName": [
            "бК0.347.458-08ТУ"
        ],
        "manufacturerName": [
            "АО «ЭКСИТОН»"
        ]
    },
    {
        "ekbName": "1526ИР13 ММ",
        "tuName": [
            "АЕЯР.431200.139-08ТУ"
        ],
        "manufacturerName": [
            "АО «МИКРОН»"
        ]
    },
    {
        "ekbName": "1526ИР2",
        "tuName": [
            "бК0.347.458-05ТУ"
        ],
        "manufacturerName": [
            "АО «НЗПП ВОСТОК»"
        ]
    },
    {
        "ekbName": "1526ИР2 ММ",
        "tuName": [
            "АЕЯР.431200.139-05ТУ"
        ],
        "manufacturerName": [
            "АО «МИКРОН»"
        ]
    },
    {
        "ekbName": "1526ИР2 ЭП",
        "tuName": [
            "АЕЯР.431200.126-12ТУ"
        ],
        "manufacturerName": [
            "АО «ЭКСИТОН»"
        ]
    },
    {
        "ekbName": "1526ИР6",
        "tuName": [
            "бК0.347.458-09ТУ"
        ],
        "manufacturerName": [
            "АО «ЭКСИТОН»"
        ]
    },
    {
        "ekbName": "1526ИР6 ММ",
        "tuName": [
            "АЕЯР.431200.139-09ТУ"
        ],
        "manufacturerName": [
            "АО «МИКРОН»"
        ]
    },
    {
        "ekbName": "1526ИР9",
        "tuName": [
            "бК0.347.458-02ТУ"
        ],
        "manufacturerName": [
            "АО «НЗПП ВОСТОК»"
        ]
    },
    {
        "ekbName": "1526ИР9 ММ",
        "tuName": [
            "АЕЯР.431200.139-02ТУ"
        ],
        "manufacturerName": [
            "АО «МИКРОН»"
        ]
    },
    {
        "ekbName": "1526ИР9 ЭП",
        "tuName": [
            "АЕЯР.431200.126-02ТУ"
        ],
        "manufacturerName": [
            "АО «ЭКСИТОН»"
        ]
    },
    {
        "ekbName": "1526КП1",
        "tuName": [
            "бК0.347.458-03ТУ"
        ],
        "manufacturerName": [
            "АО «НЗПП ВОСТОК»"
        ]
    },
    {
        "ekbName": "1526КП1 ММ",
        "tuName": [
            "АЕЯР.431200.139-03ТУ"
        ],
        "manufacturerName": [
            "АО «МИКРОН»"
        ]
    },
    {
        "ekbName": "1526КП1 ЭП",
        "tuName": [
            "АЕЯР.431200.126-03ТУ"
        ],
        "manufacturerName": [
            "АО «ЭКСИТОН»"
        ]
    },
    {
        "ekbName": "1526КП2",
        "tuName": [
            "бК0.347.458-03ТУ"
        ],
        "manufacturerName": [
            "АО «НЗПП ВОСТОК»"
        ]
    },
    {
        "ekbName": "1526КП2 ММ",
        "tuName": [
            "АЕЯР.431200.139-03ТУ"
        ],
        "manufacturerName": [
            "АО «МИКРОН»"
        ]
    },
    {
        "ekbName": "1526КП2 ЭП",
        "tuName": [
            "АЕЯР.431200.126-03ТУ"
        ],
        "manufacturerName": [
            "АО «ЭКСИТОН»"
        ]
    },
    {
        "ekbName": "1526КТ3",
        "tuName": [
            "бК0.347.458-04ТУ"
        ],
        "manufacturerName": [
            "АО «ЭКСИТОН»"
        ]
    },
    {
        "ekbName": "1526КТ3 ММ",
        "tuName": [
            "АЕЯР.431200.139-04ТУ"
        ],
        "manufacturerName": [
            "АО «МИКРОН»"
        ]
    },
    {
        "ekbName": "1526ЛА10",
        "tuName": [
            "бК0.347.458-05ТУ"
        ],
        "manufacturerName": [
            "АО «НЗПП ВОСТОК»"
        ]
    },
    {
        "ekbName": "1526ЛА10 ММ",
        "tuName": [
            "АЕЯР.431200.139-05ТУ"
        ],
        "manufacturerName": [
            "АО «МИКРОН»"
        ]
    },
    {
        "ekbName": "1526ЛА10 ЭП",
        "tuName": [
            "АЕЯР.431200.126-07ТУ"
        ],
        "manufacturerName": [
            "АО «ЭКСИТОН»"
        ]
    },
    {
        "ekbName": "1526ЛА7",
        "tuName": [
            "бК0.347.458-01ТУ"
        ],
        "manufacturerName": [
            "АО «НЗПП ВОСТОК»"
        ]
    },
    {
        "ekbName": "1526ЛА7 ММ",
        "tuName": [
            "АЕЯР.431200.139-01ТУ"
        ],
        "manufacturerName": [
            "АО «МИКРОН»"
        ]
    },
    {
        "ekbName": "1526ЛА7 ЭП",
        "tuName": [
            "АЕЯР.431200.126-01ТУ"
        ],
        "manufacturerName": [
            "АО «ЭКСИТОН»"
        ]
    },
    {
        "ekbName": "1526ЛА8",
        "tuName": [
            "бК0.347.458-01ТУ"
        ],
        "manufacturerName": [
            "АО «НЗПП ВОСТОК»"
        ]
    },
    {
        "ekbName": "1526ЛА8 ММ",
        "tuName": [
            "АЕЯР.431200.139-01ТУ"
        ],
        "manufacturerName": [
            "АО «МИКРОН»"
        ]
    },
    {
        "ekbName": "1526ЛА8 ЭП",
        "tuName": [
            "АЕЯР.431200.126-01ТУ"
        ],
        "manufacturerName": [
            "АО «ЭКСИТОН»"
        ]
    },
    {
        "ekbName": "1526ЛА9",
        "tuName": [
            "бК0.347.458-07ТУ"
        ],
        "manufacturerName": [
            "АО «ЭКСИТОН»"
        ]
    },
    {
        "ekbName": "1526ЛА9 ММ",
        "tuName": [
            "АЕЯР.431200.139-07ТУ"
        ],
        "manufacturerName": [
            "АО «МИКРОН»"
        ]
    },
    {
        "ekbName": "1526ЛЕ10",
        "tuName": [
            "бК0.347.458-07ТУ"
        ],
        "manufacturerName": [
            "АО «ЭКСИТОН»"
        ]
    },
    {
        "ekbName": "1526ЛЕ10 ММ",
        "tuName": [
            "АЕЯР.431200.139-07ТУ"
        ],
        "manufacturerName": [
            "АО «МИКРОН»"
        ]
    },
    {
        "ekbName": "1526ЛЕ5",
        "tuName": [
            "бК0.347.458-15ТУ"
        ],
        "manufacturerName": [
            "АО «ЭКСИТОН»"
        ]
    },
    {
        "ekbName": "1526ЛЕ5 ММ",
        "tuName": [
            "АЕЯР.431200.139-15ТУ"
        ],
        "manufacturerName": [
            "АО «МИКРОН»"
        ]
    },
    {
        "ekbName": "1526ЛЕ6",
        "tuName": [
            "бК0.347.458-15ТУ"
        ],
        "manufacturerName": [
            "АО «ЭКСИТОН»"
        ]
    },
    {
        "ekbName": "1526ЛЕ6 ММ",
        "tuName": [
            "АЕЯР.431200.139-15ТУ"
        ],
        "manufacturerName": [
            "АО «МИКРОН»"
        ]
    },
    {
        "ekbName": "1526ЛН1",
        "tuName": [
            "бК0.347.458-13ТУ"
        ],
        "manufacturerName": [
            "АО «ЭКСИТОН»"
        ]
    },
    {
        "ekbName": "1526ЛН1 ММ",
        "tuName": [
            "АЕЯР.431200.139-13ТУ"
        ],
        "manufacturerName": [
            "АО «МИКРОН»"
        ]
    },
    {
        "ekbName": "1526ЛН2",
        "tuName": [
            "бК0.347.458-01ТУ"
        ],
        "manufacturerName": [
            "АО «НЗПП ВОСТОК»"
        ]
    },
    {
        "ekbName": "1526ЛН2 ММ",
        "tuName": [
            "АЕЯР.431200.139-01ТУ"
        ],
        "manufacturerName": [
            "АО «МИКРОН»"
        ]
    },
    {
        "ekbName": "1526ЛН2 ЭП",
        "tuName": [
            "АЕЯР.431200.126-01ТУ"
        ],
        "manufacturerName": [
            "АО «ЭКСИТОН»"
        ]
    },
    {
        "ekbName": "1526ЛП13",
        "tuName": [
            "бК0.347.458-01ТУ"
        ],
        "manufacturerName": [
            "АО «НЗПП ВОСТОК»"
        ]
    },
    {
        "ekbName": "1526ЛП13 ММ",
        "tuName": [
            "АЕЯР.431200.139-01ТУ"
        ],
        "manufacturerName": [
            "АО «МИКРОН»"
        ]
    },
    {
        "ekbName": "1526ЛП13 ЭП",
        "tuName": [
            "АЕЯР.431200.126-01ТУ"
        ],
        "manufacturerName": [
            "АО «ЭКСИТОН»"
        ]
    },
    {
        "ekbName": "1526ЛП2",
        "tuName": [
            "бК0.347.458-15ТУ"
        ],
        "manufacturerName": [
            "АО «ЭКСИТОН»"
        ]
    },
    {
        "ekbName": "1526ЛП2 ММ",
        "tuName": [
            "АЕЯР.431200.139-15ТУ"
        ],
        "manufacturerName": [
            "АО «МИКРОН»"
        ]
    },
    {
        "ekbName": "1526ЛС2",
        "tuName": [
            "бК0.347.458-11ТУ"
        ],
        "manufacturerName": [
            "АО «ЭКСИТОН»"
        ]
    },
    {
        "ekbName": "1526ЛС2 ММ",
        "tuName": [
            "АЕЯР.431200.139-11ТУ"
        ],
        "manufacturerName": [
            "АО «МИКРОН»"
        ]
    },
    {
        "ekbName": "1526ПР1",
        "tuName": [
            "бК0.347.458-05ТУ"
        ],
        "manufacturerName": [
            "АО «НЗПП ВОСТОК»"
        ]
    },
    {
        "ekbName": "1526ПР1 ЭП",
        "tuName": [
            "АЕЯР.431200.126-10ТУ"
        ],
        "manufacturerName": [
            "АО «ЭКСИТОН»"
        ]
    },
    {
        "ekbName": "1526ПУ4",
        "tuName": [
            "бК0.347.458-11ТУ"
        ],
        "manufacturerName": [
            "АО «ЭКСИТОН»"
        ]
    },
    {
        "ekbName": "1526ПУ4 ММ",
        "tuName": [
            "АЕЯР.431200.139-11ТУ"
        ],
        "manufacturerName": [
            "АО «МИКРОН»"
        ]
    },
    {
        "ekbName": "1526ПУ6",
        "tuName": [
            "бК0.347.458-05ТУ"
        ],
        "manufacturerName": [
            "АО «НЗПП ВОСТОК»"
        ]
    },
    {
        "ekbName": "1526ПУ6 ММ",
        "tuName": [
            "АЕЯР.431200.139-05ТУ"
        ],
        "manufacturerName": [
            "АО «МИКРОН»"
        ]
    },
    {
        "ekbName": "1526ПУ6 ЭП",
        "tuName": [
            "АЕЯР.431200.126-07ТУ"
        ],
        "manufacturerName": [
            "АО «ЭКСИТОН»"
        ]
    },
    {
        "ekbName": "1526ПУ7",
        "tuName": [
            "бК0.347.458-05ТУ"
        ],
        "manufacturerName": [
            "АО «НЗПП ВОСТОК»"
        ]
    },
    {
        "ekbName": "1526ПУ7 ММ",
        "tuName": [
            "АЕЯР.431200.139-05ТУ"
        ],
        "manufacturerName": [
            "АО «МИКРОН»"
        ]
    },
    {
        "ekbName": "1526ПУ7 ЭП",
        "tuName": [
            "АЕЯР.431200.126-08ТУ"
        ],
        "manufacturerName": [
            "АО «ЭКСИТОН»"
        ]
    },
    {
        "ekbName": "1526ПУ8",
        "tuName": [
            "бК0.347.458-05ТУ"
        ],
        "manufacturerName": [
            "АО «НЗПП ВОСТОК»"
        ]
    },
    {
        "ekbName": "1526ПУ8 ММ",
        "tuName": [
            "АЕЯР.431200.139-05ТУ"
        ],
        "manufacturerName": [
            "АО «МИКРОН»"
        ]
    },
    {
        "ekbName": "1526ПУ8 ЭП",
        "tuName": [
            "АЕЯР.431200.126-08ТУ"
        ],
        "manufacturerName": [
            "АО «ЭКСИТОН»"
        ]
    },
    {
        "ekbName": "1526ПУ9 ММ",
        "tuName": [
            "АЕЯР.431200.139-20ТУ"
        ],
        "manufacturerName": [
            "АО «МИКРОН»"
        ]
    },
    {
        "ekbName": "1526ПУ91",
        "tuName": [
            "АЕЯР.431200.126-14ТУ"
        ],
        "manufacturerName": [
            "АО «ЭКСИТОН»"
        ]
    },
    {
        "ekbName": "1526СА1",
        "tuName": [
            "бК0.347.458-06ТУ"
        ],
        "manufacturerName": [
            "АО «ЭКСИТОН»"
        ]
    },
    {
        "ekbName": "1526ТВ1",
        "tuName": [
            "бК0.347.458-16ТУ"
        ],
        "manufacturerName": [
            "АО «ЭКСИТОН»"
        ]
    },
    {
        "ekbName": "1526ТВ1 ММ",
        "tuName": [
            "АЕЯР.431200.139-16ТУ"
        ],
        "manufacturerName": [
            "АО «МИКРОН»"
        ]
    },
    {
        "ekbName": "1526ТЛ1",
        "tuName": [
            "бК0.347.458-22ТУ"
        ],
        "manufacturerName": [
            "АО «ЭКСИТОН»"
        ]
    },
    {
        "ekbName": "1526ТЛ1 ММ",
        "tuName": [
            "АЕЯР.431200.139-22ТУ"
        ],
        "manufacturerName": [
            "АО «МИКРОН»"
        ]
    },
    {
        "ekbName": "1526ТМ2",
        "tuName": [
            "бК0.347.458-02ТУ"
        ],
        "manufacturerName": [
            "АО «НЗПП ВОСТОК»"
        ]
    },
    {
        "ekbName": "1526ТМ2 ММ",
        "tuName": [
            "АЕЯР.431200.139-02ТУ"
        ],
        "manufacturerName": [
            "АО «МИКРОН»"
        ]
    },
    {
        "ekbName": "1526ТМ2 ЭП",
        "tuName": [
            "АЕЯР.431200.126-02ТУ"
        ],
        "manufacturerName": [
            "АО «ЭКСИТОН»"
        ]
    },
    {
        "ekbName": "1526ТМ3",
        "tuName": [
            "бК0.347.458-12ТУ"
        ],
        "manufacturerName": [
            "АО «ЭКСИТОН»"
        ]
    },
    {
        "ekbName": "1526ТМ3 ММ",
        "tuName": [
            "АЕЯР.431200.139-12ТУ"
        ],
        "manufacturerName": [
            "АО «МИКРОН»"
        ]
    },
    {
        "ekbName": "1526ТР2",
        "tuName": [
            "бК0.347.458-12ТУ"
        ],
        "manufacturerName": [
            "АО «ЭКСИТОН»"
        ]
    },
    {
        "ekbName": "1526ТР2 ММ",
        "tuName": [
            "АЕЯР.431200.139-12ТУ"
        ],
        "manufacturerName": [
            "АО «МИКРОН»"
        ]
    },
    {
        "ekbName": "Б1526ИД1-4",
        "tuName": [
            "бК0.347.458-05ТУ"
        ],
        "manufacturerName": [
            "АО «НЗПП ВОСТОК»"
        ]
    },
    {
        "ekbName": "Б1526ИЕ10-1 ЭП",
        "tuName": [
            "АЕЯР.431200.127-03ТУ"
        ],
        "manufacturerName": [
            "АО «ЭКСИТОН»"
        ]
    },
    {
        "ekbName": "Б1526ИЕ10-1Н ЭП",
        "tuName": [
            "АЕЯР.431200.127-03ТУ",
            "РМ 11 091.926"
        ],
        "manufacturerName": [
            "АО «ЭКСИТОН»"
        ]
    },
    {
        "ekbName": "Б1526ИЕ11-1 ЭП",
        "tuName": [
            "АЕЯР.431200.127-03ТУ"
        ],
        "manufacturerName": [
            "АО «ЭКСИТОН»"
        ]
    },
    {
        "ekbName": "Б1526ИЕ11-1Н ЭП",
        "tuName": [
            "АЕЯР.431200.127-03ТУ",
            "РМ 11 091.926"
        ],
        "manufacturerName": [
            "АО «ЭКСИТОН»"
        ]
    },
    {
        "ekbName": "Б1526ИЕ11-4",
        "tuName": [
            "бК0.347.458-02ТУ"
        ],
        "manufacturerName": [
            "АО «НЗПП ВОСТОК»"
        ]
    },
    {
        "ekbName": "Б1526ИЕ14-4",
        "tuName": [
            "бК0.347.458-02ТУ"
        ],
        "manufacturerName": [
            "АО «НЗПП ВОСТОК»"
        ]
    },
    {
        "ekbName": "Б1526ИЕ15-4",
        "tuName": [
            "бК0.347.458-05ТУ"
        ],
        "manufacturerName": [
            "АО «НЗПП ВОСТОК»"
        ]
    },
    {
        "ekbName": "Б1526ИЕ19-4",
        "tuName": [
            "бК0.347.458-05ТУ"
        ],
        "manufacturerName": [
            "АО «НЗПП ВОСТОК»"
        ]
    },
    {
        "ekbName": "Б1526ИК1-4",
        "tuName": [
            "бК0.347.458-05ТУ"
        ],
        "manufacturerName": [
            "АО «НЗПП ВОСТОК»"
        ]
    },
    {
        "ekbName": "Б1526ИМ1-4",
        "tuName": [
            "бК0.347.458-03ТУ"
        ],
        "manufacturerName": [
            "АО «НЗПП ВОСТОК»"
        ]
    },
    {
        "ekbName": "Б1526ИП2-1 ЭП",
        "tuName": [
            "АЕЯР.431200.127-08ТУ"
        ],
        "manufacturerName": [
            "АО «ЭКСИТОН»"
        ]
    },
    {
        "ekbName": "Б1526ИП2-1Н ЭП",
        "tuName": [
            "АЕЯР.431200.127-08ТУ",
            "РМ 11 091.926"
        ],
        "manufacturerName": [
            "АО «ЭКСИТОН»"
        ]
    },
    {
        "ekbName": "Б1526ИП3-4",
        "tuName": [
            "бК0.347.458-05ТУ"
        ],
        "manufacturerName": [
            "АО «НЗПП ВОСТОК»"
        ]
    },
    {
        "ekbName": "Б1526ИП4-4",
        "tuName": [
            "бК0.347.458-05ТУ"
        ],
        "manufacturerName": [
            "АО «НЗПП ВОСТОК»"
        ]
    },
    {
        "ekbName": "Б1526ИП6-4",
        "tuName": [
            "бК0.347.458-05ТУ"
        ],
        "manufacturerName": [
            "АО «НЗПП ВОСТОК»"
        ]
    },
    {
        "ekbName": "Б1526ИР2-1 ЭП",
        "tuName": [
            "АЕЯР.431200.127-06ТУ"
        ],
        "manufacturerName": [
            "АО «ЭКСИТОН»"
        ]
    },
    {
        "ekbName": "Б1526ИР2-1Н ЭП",
        "tuName": [
            "АЕЯР.431200.127-06ТУ",
            "РМ 11 091.926"
        ],
        "manufacturerName": [
            "АО «ЭКСИТОН»"
        ]
    },
    {
        "ekbName": "Б1526ИР2-4",
        "tuName": [
            "бК0.347.458-05ТУ"
        ],
        "manufacturerName": [
            "АО «НЗПП ВОСТОК»"
        ]
    },
    {
        "ekbName": "Б1526ИР9-1 ЭП",
        "tuName": [
            "АЕЯР.431200.127-06ТУ"
        ],
        "manufacturerName": [
            "АО «ЭКСИТОН»"
        ]
    },
    {
        "ekbName": "Б1526ИР9-1Н ЭП",
        "tuName": [
            "АЕЯР.431200.127-06ТУ",
            "РМ 11 091.926"
        ],
        "manufacturerName": [
            "АО «ЭКСИТОН»"
        ]
    },
    {
        "ekbName": "Б1526ИР9-4",
        "tuName": [
            "бК0.347.458-02ТУ"
        ],
        "manufacturerName": [
            "АО «НЗПП ВОСТОК»"
        ]
    },
    {
        "ekbName": "Б1526КП1-4",
        "tuName": [
            "бК0.347.458-03ТУ"
        ],
        "manufacturerName": [
            "АО «НЗПП ВОСТОК»"
        ]
    },
    {
        "ekbName": "Б1526КП2-1 ЭП",
        "tuName": [
            "АЕЯР.431200.127-04ТУ"
        ],
        "manufacturerName": [
            "АО «ЭКСИТОН»"
        ]
    },
    {
        "ekbName": "Б1526КП2-1Н ЭП",
        "tuName": [
            "АЕЯР.431200.127-04ТУ",
            "РМ 11 091.926"
        ],
        "manufacturerName": [
            "АО «ЭКСИТОН»"
        ]
    },
    {
        "ekbName": "Б1526КП2-4",
        "tuName": [
            "бК0.347.458-03ТУ"
        ],
        "manufacturerName": [
            "АО «НЗПП ВОСТОК»"
        ]
    },
    {
        "ekbName": "Б1526КТ3-1 ЭП",
        "tuName": [
            "АЕЯР.431200.127-04ТУ"
        ],
        "manufacturerName": [
            "АО «ЭКСИТОН»"
        ]
    },
    {
        "ekbName": "Б1526КТ3-1Н ЭП",
        "tuName": [
            "АЕЯР.431200.127-04ТУ",
            "РМ 11 091.926"
        ],
        "manufacturerName": [
            "АО «ЭКСИТОН»"
        ]
    },
    {
        "ekbName": "Б1526ЛА10-1 ЭП",
        "tuName": [
            "АЕЯР.431200.127-01ТУ"
        ],
        "manufacturerName": [
            "АО «ЭКСИТОН»"
        ]
    },
    {
        "ekbName": "Б1526ЛА10-1Н ЭП",
        "tuName": [
            "АЕЯР.431200.127-01ТУ",
            "РМ 11 091.926"
        ],
        "manufacturerName": [
            "АО «ЭКСИТОН»"
        ]
    },
    {
        "ekbName": "Б1526ЛА10-4",
        "tuName": [
            "бК0.347.458-05ТУ"
        ],
        "manufacturerName": [
            "АО «НЗПП ВОСТОК»"
        ]
    },
    {
        "ekbName": "Б1526ЛА7-1 ЭП",
        "tuName": [
            "АЕЯР.431200.127-01ТУ"
        ],
        "manufacturerName": [
            "АО «ЭКСИТОН»"
        ]
    },
    {
        "ekbName": "Б1526ЛА7-1Н ЭП",
        "tuName": [
            "АЕЯР.431200.127-01ТУ",
            "РМ 11 091.926"
        ],
        "manufacturerName": [
            "АО «ЭКСИТОН»"
        ]
    },
    {
        "ekbName": "Б1526ЛА7-4",
        "tuName": [
            "бК0.347.458-01ТУ"
        ],
        "manufacturerName": [
            "АО «НЗПП ВОСТОК»"
        ]
    },
    {
        "ekbName": "Б1526ЛА8-1 ЭП",
        "tuName": [
            "АЕЯР.431200.127-01ТУ"
        ],
        "manufacturerName": [
            "АО «ЭКСИТОН»"
        ]
    },
    {
        "ekbName": "Б1526ЛА8-1Н ЭП",
        "tuName": [
            "АЕЯР.431200.127-01ТУ",
            "РМ 11 091.926"
        ],
        "manufacturerName": [
            "АО «ЭКСИТОН»"
        ]
    },
    {
        "ekbName": "Б1526ЛА8-4",
        "tuName": [
            "бК0.347.458-01ТУ"
        ],
        "manufacturerName": [
            "АО «НЗПП ВОСТОК»"
        ]
    },
    {
        "ekbName": "Б1526ЛА9-1 ЭП",
        "tuName": [
            "АЕЯР.431200.127-02ТУ"
        ],
        "manufacturerName": [
            "АО «ЭКСИТОН»"
        ]
    },
    {
        "ekbName": "Б1526ЛА9-1Н ЭП",
        "tuName": [
            "АЕЯР.431200.127-02ТУ",
            "РМ 11 091.926"
        ],
        "manufacturerName": [
            "АО «ЭКСИТОН»"
        ]
    },
    {
        "ekbName": "Б1526ЛЕ10-1 ЭП",
        "tuName": [
            "АЕЯР.431200.127-02ТУ"
        ],
        "manufacturerName": [
            "АО «ЭКСИТОН»"
        ]
    },
    {
        "ekbName": "Б1526ЛЕ10-1Н ЭП",
        "tuName": [
            "АЕЯР.431200.127-02ТУ",
            "РМ 11 091.926"
        ],
        "manufacturerName": [
            "АО «ЭКСИТОН»"
        ]
    },
    {
        "ekbName": "Б1526ЛЕ5-1 ЭП",
        "tuName": [
            "АЕЯР.431200.127-02ТУ"
        ],
        "manufacturerName": [
            "АО «ЭКСИТОН»"
        ]
    },
    {
        "ekbName": "Б1526ЛЕ5-1Н ЭП",
        "tuName": [
            "АЕЯР.431200.127-02ТУ",
            "РМ 11 091.926"
        ],
        "manufacturerName": [
            "АО «ЭКСИТОН»"
        ]
    },
    {
        "ekbName": "Б1526ЛЕ6-1 ЭП",
        "tuName": [
            "АЕЯР.431200.127-02ТУ"
        ],
        "manufacturerName": [
            "АО «ЭКСИТОН»"
        ]
    },
    {
        "ekbName": "Б1526ЛЕ6-1Н ЭП",
        "tuName": [
            "АЕЯР.431200.127-02ТУ",
            "РМ 11 091.926"
        ],
        "manufacturerName": [
            "АО «ЭКСИТОН»"
        ]
    },
    {
        "ekbName": "Б1526ЛН1-1 ЭП",
        "tuName": [
            "АЕЯР.431200.127-08ТУ"
        ],
        "manufacturerName": [
            "АО «ЭКСИТОН»"
        ]
    },
    {
        "ekbName": "Б1526ЛН1-1Н ЭП",
        "tuName": [
            "АЕЯР.431200.127-08ТУ",
            "РМ 11 091.926"
        ],
        "manufacturerName": [
            "АО «ЭКСИТОН»"
        ]
    },
    {
        "ekbName": "Б1526ЛН2-1 ЭП",
        "tuName": [
            "АЕЯР.431200.127-01ТУ"
        ],
        "manufacturerName": [
            "АО «ЭКСИТОН»"
        ]
    },
    {
        "ekbName": "Б1526ЛН2-1Н ЭП",
        "tuName": [
            "АЕЯР.431200.127-01ТУ",
            "РМ 11 091.926"
        ],
        "manufacturerName": [
            "АО «ЭКСИТОН»"
        ]
    },
    {
        "ekbName": "Б1526ЛН2-4",
        "tuName": [
            "бК0.347.458-01ТУ"
        ],
        "manufacturerName": [
            "АО «НЗПП ВОСТОК»"
        ]
    },
    {
        "ekbName": "Б1526ЛП13-1 ЭП",
        "tuName": [
            "АЕЯР.431200.127-10ТУ"
        ],
        "manufacturerName": [
            "АО «ЭКСИТОН»"
        ]
    },
    {
        "ekbName": "Б1526ЛП13-1Н ЭП",
        "tuName": [
            "АЕЯР.431200.127-10ТУ",
            "РМ 11 091.926"
        ],
        "manufacturerName": [
            "АО «ЭКСИТОН»"
        ]
    },
    {
        "ekbName": "Б1526ЛП13-4",
        "tuName": [
            "бК0.347.458-01ТУ"
        ],
        "manufacturerName": [
            "АО «НЗПП ВОСТОК»"
        ]
    },
    {
        "ekbName": "Б1526ЛП2-1 ЭП",
        "tuName": [
            "АЕЯР.431200.127-08ТУ"
        ],
        "manufacturerName": [
            "АО «ЭКСИТОН»"
        ]
    },
    {
        "ekbName": "Б1526ЛП2-1Н ЭП",
        "tuName": [
            "АЕЯР.431200.127-08ТУ",
            "РМ 11 091.926"
        ],
        "manufacturerName": [
            "АО «ЭКСИТОН»"
        ]
    },
    {
        "ekbName": "Б1526ЛС2-1 ЭП",
        "tuName": [
            "АЕЯР.431200.127-08ТУ"
        ],
        "manufacturerName": [
            "АО «ЭКСИТОН»"
        ]
    },
    {
        "ekbName": "Б1526ЛС2-1Н ЭП",
        "tuName": [
            "АЕЯР.431200.127-08ТУ",
            "РМ 11 091.926"
        ],
        "manufacturerName": [
            "АО «ЭКСИТОН»"
        ]
    },
    {
        "ekbName": "Б1526ПР1-4",
        "tuName": [
            "бК0.347.458-05ТУ"
        ],
        "manufacturerName": [
            "АО «НЗПП ВОСТОК»"
        ]
    },
    {
        "ekbName": "Б1526ПУ4-1 ЭП",
        "tuName": [
            "АЕЯР.431200.127-09ТУ"
        ],
        "manufacturerName": [
            "АО «ЭКСИТОН»"
        ]
    },
    {
        "ekbName": "Б1526ПУ4-1Н ЭП",
        "tuName": [
            "АЕЯР.431200.127-09ТУ",
            "РМ 11 091.926"
        ],
        "manufacturerName": [
            "АО «ЭКСИТОН»"
        ]
    },
    {
        "ekbName": "Б1526ПУ6-4",
        "tuName": [
            "бК0.347.458-05ТУ"
        ],
        "manufacturerName": [
            "АО «НЗПП ВОСТОК»"
        ]
    },
    {
        "ekbName": "Б1526ПУ7-4",
        "tuName": [
            "бК0.347.458-05ТУ"
        ],
        "manufacturerName": [
            "АО «НЗПП ВОСТОК»"
        ]
    },
    {
        "ekbName": "Б1526ПУ8-4",
        "tuName": [
            "бК0.347.458-05ТУ"
        ],
        "manufacturerName": [
            "АО «НЗПП ВОСТОК»"
        ]
    },
    {
        "ekbName": "Б1526ПУ91-1 ЭП",
        "tuName": [
            "АЕЯР.431200.127-07ТУ"
        ],
        "manufacturerName": [
            "АО «ЭКСИТОН»"
        ]
    },
    {
        "ekbName": "Б1526ПУ91-1Н",
        "tuName": [
            "АЕЯР.431200.127-07ТУ",
            "РМ 11 091.926"
        ],
        "manufacturerName": [
            "АО «ЭКСИТОН»"
        ]
    },
    {
        "ekbName": "Б1526ТВ1-1 ЭП",
        "tuName": [
            "АЕЯР.431200.127-09ТУ"
        ],
        "manufacturerName": [
            "АО «ЭКСИТОН»"
        ]
    },
    {
        "ekbName": "Б1526ТВ1-1Н ЭП",
        "tuName": [
            "АЕЯР.431200.127-09ТУ",
            "РМ 11 091.926"
        ],
        "manufacturerName": [
            "АО «ЭКСИТОН»"
        ]
    },
    {
        "ekbName": "Б1526ТЛ1-1 ЭП",
        "tuName": [
            "АЕЯР.431200.127-05ТУ"
        ],
        "manufacturerName": [
            "АО «ЭКСИТОН»"
        ]
    },
    {
        "ekbName": "Б1526ТЛ1-1Н ЭП",
        "tuName": [
            "АЕЯР.431200.127-05ТУ",
            "РМ 11 091.926"
        ],
        "manufacturerName": [
            "АО «ЭКСИТОН»"
        ]
    },
    {
        "ekbName": "Б1526ТМ2-1 ЭП",
        "tuName": [
            "АЕЯР.431200.127-05ТУ"
        ],
        "manufacturerName": [
            "АО «ЭКСИТОН»"
        ]
    },
    {
        "ekbName": "Б1526ТМ2-1Н ЭП",
        "tuName": [
            "АЕЯР.431200.127-05ТУ",
            "РМ 11 091.926"
        ],
        "manufacturerName": [
            "АО «ЭКСИТОН»"
        ]
    },
    {
        "ekbName": "Б1526ТМ2-4",
        "tuName": [
            "бК0.347.458-02ТУ"
        ],
        "manufacturerName": [
            "АО «НЗПП ВОСТОК»"
        ]
    },
    {
        "ekbName": "Б1526ТМ3-1 ЭП",
        "tuName": [
            "АЕЯР.431200.127-09ТУ"
        ],
        "manufacturerName": [
            "АО «ЭКСИТОН»"
        ]
    },
    {
        "ekbName": "Б1526ТМ3-1Н ЭП",
        "tuName": [
            "АЕЯР.431200.127-09ТУ",
            "РМ 11 091.926"
        ],
        "manufacturerName": [
            "АО «ЭКСИТОН»"
        ]
    },
    {
        "ekbName": "Б1526ТР2-1 ЭП",
        "tuName": [
            "АЕЯР.431200.127-09ТУ"
        ],
        "manufacturerName": [
            "АО «ЭКСИТОН»"
        ]
    },
    {
        "ekbName": "Б1526ТР2-1Н ЭП",
        "tuName": [
            "АЕЯР.431200.127-09ТУ",
            "РМ 11 091.926"
        ],
        "manufacturerName": [
            "АО «ЭКСИТОН»"
        ]
    },
    {
        "ekbName": "ОС 1526ИД1",
        "tuName": [
            "бК0.347.637-05СТУ"
        ],
        "manufacturerName": [
            "АО «НЗПП ВОСТОК»"
        ]
    },
    {
        "ekbName": "ОС 1526ИЕ11",
        "tuName": [
            "бК0.347.637-02СТУ"
        ],
        "manufacturerName": [
            "АО «НЗПП ВОСТОК»"
        ]
    },
    {
        "ekbName": "ОС 1526ИЕ14",
        "tuName": [
            "бК0.347.637-02СТУ"
        ],
        "manufacturerName": [
            "АО «НЗПП ВОСТОК»"
        ]
    },
    {
        "ekbName": "ОС 1526ИЕ15",
        "tuName": [
            "бК0.347.637-05СТУ"
        ],
        "manufacturerName": [
            "АО «НЗПП ВОСТОК»"
        ]
    },
    {
        "ekbName": "ОС 1526ИЕ19",
        "tuName": [
            "бК0.347.637-05СТУ"
        ],
        "manufacturerName": [
            "АО «НЗПП ВОСТОК»"
        ]
    },
    {
        "ekbName": "ОС 1526ИК1",
        "tuName": [
            "бК0.347.637-05СТУ"
        ],
        "manufacturerName": [
            "АО «НЗПП ВОСТОК»"
        ]
    },
    {
        "ekbName": "ОС 1526ИМ1",
        "tuName": [
            "бК0.347.637-03СТУ"
        ],
        "manufacturerName": [
            "АО «НЗПП ВОСТОК»"
        ]
    },
    {
        "ekbName": "ОС 1526ИП3",
        "tuName": [
            "бК0.347.637-05СТУ"
        ],
        "manufacturerName": [
            "АО «НЗПП ВОСТОК»"
        ]
    },
    {
        "ekbName": "ОС 1526ИП4",
        "tuName": [
            "бК0.347.637-05СТУ"
        ],
        "manufacturerName": [
            "АО «НЗПП ВОСТОК»"
        ]
    },
    {
        "ekbName": "ОС 1526ИП6",
        "tuName": [
            "бК0.347.637-05СТУ"
        ],
        "manufacturerName": [
            "АО «НЗПП ВОСТОК»"
        ]
    },
    {
        "ekbName": "ОС 1526ИР2",
        "tuName": [
            "бК0.347.637-05СТУ"
        ],
        "manufacturerName": [
            "АО «НЗПП ВОСТОК»"
        ]
    },
    {
        "ekbName": "ОС 1526ИР9",
        "tuName": [
            "бК0.347.637-02СТУ"
        ],
        "manufacturerName": [
            "АО «НЗПП ВОСТОК»"
        ]
    },
    {
        "ekbName": "ОС 1526КП1",
        "tuName": [
            "бК0.347.637-03СТУ"
        ],
        "manufacturerName": [
            "АО «НЗПП ВОСТОК»"
        ]
    },
    {
        "ekbName": "ОС 1526КП2",
        "tuName": [
            "бК0.347.637-03СТУ"
        ],
        "manufacturerName": [
            "АО «НЗПП ВОСТОК»"
        ]
    },
    {
        "ekbName": "ОС 1526ЛА10",
        "tuName": [
            "бК0.347.637-05СТУ"
        ],
        "manufacturerName": [
            "АО «НЗПП ВОСТОК»"
        ]
    },
    {
        "ekbName": "ОС 1526ЛА7",
        "tuName": [
            "бК0.347.637-01СТУ"
        ],
        "manufacturerName": [
            "АО «НЗПП ВОСТОК»"
        ]
    },
    {
        "ekbName": "ОС 1526ЛА8",
        "tuName": [
            "бК0.347.637-01СТУ"
        ],
        "manufacturerName": [
            "АО «НЗПП ВОСТОК»"
        ]
    },
    {
        "ekbName": "ОС 1526ЛН2",
        "tuName": [
            "бК0.347.637-01СТУ"
        ],
        "manufacturerName": [
            "АО «НЗПП ВОСТОК»"
        ]
    },
    {
        "ekbName": "ОС 1526ЛП13",
        "tuName": [
            "бК0.347.637-01СТУ"
        ],
        "manufacturerName": [
            "АО «НЗПП ВОСТОК»"
        ]
    },
    {
        "ekbName": "ОС 1526ПР1",
        "tuName": [
            "бК0.347.637-05СТУ"
        ],
        "manufacturerName": [
            "АО «НЗПП ВОСТОК»"
        ]
    },
    {
        "ekbName": "ОС 1526ПУ6",
        "tuName": [
            "бК0.347.637-05СТУ"
        ],
        "manufacturerName": [
            "АО «НЗПП ВОСТОК»"
        ]
    },
    {
        "ekbName": "ОС 1526ПУ7",
        "tuName": [
            "бК0.347.637-05СТУ"
        ],
        "manufacturerName": [
            "АО «НЗПП ВОСТОК»"
        ]
    },
    {
        "ekbName": "ОС 1526ПУ8",
        "tuName": [
            "бК0.347.637-05СТУ"
        ],
        "manufacturerName": [
            "АО «НЗПП ВОСТОК»"
        ]
    },
    {
        "ekbName": "ОС 1526ТМ2",
        "tuName": [
            "бК0.347.637-02СТУ"
        ],
        "manufacturerName": [
            "АО «НЗПП ВОСТОК»"
        ]
    },
    {
        "ekbName": "ОСМ 1526АГ1",
        "tuName": [
            "бК0.347.458-21ТУ",
            "П0.070.052"
        ],
        "manufacturerName": [
            "АО «ЭКСИТОН»"
        ]
    },
    {
        "ekbName": "ОСМ 1526ИД1",
        "tuName": [
            "бК0.347.458-05ТУ",
            "П0.070.052"
        ],
        "manufacturerName": [
            "АО «НЗПП ВОСТОК»"
        ]
    },
    {
        "ekbName": "ОСМ 1526ИД1 ММ",
        "tuName": [
            "АЕЯР.431200.139-05ТУ",
            "П0.070.052"
        ],
        "manufacturerName": [
            "АО «МИКРОН»"
        ]
    },
    {
        "ekbName": "ОСМ 1526ИД1 ЭП",
        "tuName": [
            "АЕЯР.431200.126-12ТУ",
            "П0.070.052"
        ],
        "manufacturerName": [
            "АО «ЭКСИТОН»"
        ]
    },
    {
        "ekbName": "ОСМ 1526ИЕ10",
        "tuName": [
            "бК0.347.458-13ТУ",
            "П0.070.052"
        ],
        "manufacturerName": [
            "АО «ЭКСИТОН»"
        ]
    },
    {
        "ekbName": "ОСМ 1526ИЕ10 ММ",
        "tuName": [
            "АЕЯР.431200.139-13ТУ",
            "П0.070.052"
        ],
        "manufacturerName": [
            "АО «МИКРОН»"
        ]
    },
    {
        "ekbName": "ОСМ 1526ИЕ11",
        "tuName": [
            "бК0.347.458-02ТУ",
            "П0.070.052"
        ],
        "manufacturerName": [
            "АО «НЗПП ВОСТОК»"
        ]
    },
    {
        "ekbName": "ОСМ 1526ИЕ11 ММ",
        "tuName": [
            "АЕЯР.431200.139-02ТУ",
            "П0.070.052"
        ],
        "manufacturerName": [
            "АО «МИКРОН»"
        ]
    },
    {
        "ekbName": "ОСМ 1526ИЕ11 ЭП",
        "tuName": [
            "АЕЯР.431200.126-02ТУ",
            "П0.070.052"
        ],
        "manufacturerName": [
            "АО «ЭКСИТОН»"
        ]
    },
    {
        "ekbName": "ОСМ 1526ИЕ14",
        "tuName": [
            "бК0.347.458-02ТУ",
            "П0.070.052"
        ],
        "manufacturerName": [
            "АО «НЗПП ВОСТОК»"
        ]
    },
    {
        "ekbName": "ОСМ 1526ИЕ14 ММ",
        "tuName": [
            "АЕЯР.431200.139-02ТУ",
            "П0.070.052"
        ],
        "manufacturerName": [
            "АО «МИКРОН»"
        ]
    },
    {
        "ekbName": "ОСМ 1526ИЕ14 ЭП",
        "tuName": [
            "АЕЯР.431200.126-02ТУ",
            "П0.070.052"
        ],
        "manufacturerName": [
            "АО «ЭКСИТОН»"
        ]
    },
    {
        "ekbName": "ОСМ 1526ИЕ15",
        "tuName": [
            "бК0.347.458-05ТУ",
            "П0.070.052"
        ],
        "manufacturerName": [
            "АО «НЗПП ВОСТОК»"
        ]
    },
    {
        "ekbName": "ОСМ 1526ИЕ15 ЭП",
        "tuName": [
            "АЕЯР.431200.126-11ТУ",
            "П0.070.052"
        ],
        "manufacturerName": [
            "АО «ЭКСИТОН»"
        ]
    },
    {
        "ekbName": "ОСМ 1526ИЕ19",
        "tuName": [
            "бК0.347.458-05ТУ",
            "П0.070.052"
        ],
        "manufacturerName": [
            "АО «НЗПП ВОСТОК»"
        ]
    },
    {
        "ekbName": "ОСМ 1526ИЕ19 ЭП",
        "tuName": [
            "АЕЯР.431200.126-11ТУ",
            "П0.070.052"
        ],
        "manufacturerName": [
            "АО «ЭКСИТОН»"
        ]
    },
    {
        "ekbName": "ОСМ 1526ИЕ9",
        "tuName": [
            "бК0.347.458-12ТУ",
            "П0.070.052"
        ],
        "manufacturerName": [
            "АО «ЭКСИТОН»"
        ]
    },
    {
        "ekbName": "ОСМ 1526ИК1",
        "tuName": [
            "бК0.347.458-05ТУ",
            "П0.070.052"
        ],
        "manufacturerName": [
            "АО «НЗПП ВОСТОК»"
        ]
    },
    {
        "ekbName": "ОСМ 1526ИК1 ММ",
        "tuName": [
            "АЕЯР.431200.139-05ТУ",
            "П0.070.052"
        ],
        "manufacturerName": [
            "АО «МИКРОН»"
        ]
    },
    {
        "ekbName": "ОСМ 1526ИК1 ЭП",
        "tuName": [
            "АЕЯР.431200.126-13ТУ",
            "П0.070.052"
        ],
        "manufacturerName": [
            "АО «ЭКСИТОН»"
        ]
    },
    {
        "ekbName": "ОСМ 1526ИМ1",
        "tuName": [
            "бК0.347.458-03ТУ",
            "П0.070.052"
        ],
        "manufacturerName": [
            "АО «НЗПП ВОСТОК»"
        ]
    },
    {
        "ekbName": "ОСМ 1526ИМ1 ММ",
        "tuName": [
            "АЕЯР.431200.139-03ТУ",
            "П0.070.052"
        ],
        "manufacturerName": [
            "АО «МИКРОН»"
        ]
    },
    {
        "ekbName": "ОСМ 1526ИМ1 ЭП",
        "tuName": [
            "АЕЯР.431200.126-03ТУ",
            "П0.070.052"
        ],
        "manufacturerName": [
            "АО «ЭКСИТОН»"
        ]
    },
    {
        "ekbName": "ОСМ 1526ИП2",
        "tuName": [
            "бК0.347.458-13ТУ",
            "П0.070.052"
        ],
        "manufacturerName": [
            "АО «ЭКСИТОН»"
        ]
    },
    {
        "ekbName": "ОСМ 1526ИП2 ММ",
        "tuName": [
            "АЕЯР.431200.139-13ТУ",
            "П0.070.052"
        ],
        "manufacturerName": [
            "АО «МИКРОН»"
        ]
    },
    {
        "ekbName": "ОСМ 1526ИП3",
        "tuName": [
            "бК0.347.458-05ТУ",
            "П0.070.052"
        ],
        "manufacturerName": [
            "АО «НЗПП ВОСТОК»"
        ]
    },
    {
        "ekbName": "ОСМ 1526ИП3 ММ",
        "tuName": [
            "АЕЯР.431200.139-05ТУ",
            "П0.070.052"
        ],
        "manufacturerName": [
            "АО «МИКРОН»"
        ]
    },
    {
        "ekbName": "ОСМ 1526ИП3 ЭП",
        "tuName": [
            "АЕЯР.431200.126-09ТУ",
            "П0.070.052"
        ],
        "manufacturerName": [
            "АО «ЭКСИТОН»"
        ]
    },
    {
        "ekbName": "ОСМ 1526ИП4",
        "tuName": [
            "бК0.347.458-05ТУ",
            "П0.070.052"
        ],
        "manufacturerName": [
            "АО «НЗПП ВОСТОК»"
        ]
    },
    {
        "ekbName": "ОСМ 1526ИП4 ММ",
        "tuName": [
            "АЕЯР.431200.139-05ТУ",
            "П0.070.052"
        ],
        "manufacturerName": [
            "АО «МИКРОН»"
        ]
    },
    {
        "ekbName": "ОСМ 1526ИП4 ЭП",
        "tuName": [
            "АЕЯР.431200.126-09ТУ",
            "П0.070.052"
        ],
        "manufacturerName": [
            "АО «ЭКСИТОН»"
        ]
    },
    {
        "ekbName": "ОСМ 1526ИП5 ЭП",
        "tuName": [
            "АЕЯР.431200.126-04ТУ",
            "П0.070.052"
        ],
        "manufacturerName": [
            "АО «ЭКСИТОН»"
        ]
    },
    {
        "ekbName": "ОСМ 1526ИП6",
        "tuName": [
            "бК0.347.458-05ТУ",
            "П0.070.052"
        ],
        "manufacturerName": [
            "АО «НЗПП ВОСТОК»"
        ]
    },
    {
        "ekbName": "ОСМ 1526ИП6 ММ",
        "tuName": [
            "АЕЯР.431200.139-05ТУ",
            "П0.070.052"
        ],
        "manufacturerName": [
            "АО «МИКРОН»"
        ]
    },
    {
        "ekbName": "ОСМ 1526ИП6 ЭП",
        "tuName": [
            "АЕЯР.431200.126-10ТУ",
            "П0.070.052"
        ],
        "manufacturerName": [
            "АО «ЭКСИТОН»"
        ]
    },
    {
        "ekbName": "ОСМ 1526ИР1",
        "tuName": [
            "бК0.347.458-10ТУ",
            "П0.070.052"
        ],
        "manufacturerName": [
            "АО «ЭКСИТОН»"
        ]
    },
    {
        "ekbName": "ОСМ 1526ИР1 ММ",
        "tuName": [
            "АЕЯР.431200.139-10ТУ",
            "П0.070.052"
        ],
        "manufacturerName": [
            "АО «МИКРОН»"
        ]
    },
    {
        "ekbName": "ОСМ 1526ИР11",
        "tuName": [
            "бК0.347.458-14ТУ",
            "П0.070.052"
        ],
        "manufacturerName": [
            "АО «ЭКСИТОН»"
        ]
    },
    {
        "ekbName": "ОСМ 1526ИР11 ММ",
        "tuName": [
            "АЕЯР.431200.139-14ТУ",
            "П0.070.052"
        ],
        "manufacturerName": [
            "АО «МИКРОН»"
        ]
    },
    {
        "ekbName": "ОСМ 1526ИР12 ЭП",
        "tuName": [
            "АЕЯР.431200.126-05ТУ",
            "П0.070.052"
        ],
        "manufacturerName": [
            "АО «ЭКСИТОН»"
        ]
    },
    {
        "ekbName": "ОСМ 1526ИР13",
        "tuName": [
            "бК0.347.458-08ТУ",
            "П0.070.052"
        ],
        "manufacturerName": [
            "АО «ЭКСИТОН»"
        ]
    },
    {
        "ekbName": "ОСМ 1526ИР2",
        "tuName": [
            "бК0.347.458-05ТУ",
            "П0.070.052"
        ],
        "manufacturerName": [
            "АО «НЗПП ВОСТОК»"
        ]
    },
    {
        "ekbName": "ОСМ 1526ИР2 ММ",
        "tuName": [
            "АЕЯР.431200.139-05ТУ",
            "П0.070.052"
        ],
        "manufacturerName": [
            "АО «МИКРОН»"
        ]
    },
    {
        "ekbName": "ОСМ 1526ИР2 ЭП",
        "tuName": [
            "АЕЯР.431200.126-12ТУ",
            "П0.070.052"
        ],
        "manufacturerName": [
            "АО «ЭКСИТОН»"
        ]
    },
    {
        "ekbName": "ОСМ 1526ИР6",
        "tuName": [
            "бК0.347.458-09ТУ",
            "П0.070.052"
        ],
        "manufacturerName": [
            "АО «ЭКСИТОН»"
        ]
    },
    {
        "ekbName": "ОСМ 1526ИР6 ММ",
        "tuName": [
            "АЕЯР.431200.139-09ТУ",
            "П0.070.052"
        ],
        "manufacturerName": [
            "АО «МИКРОН»"
        ]
    },
    {
        "ekbName": "ОСМ 1526ИР9",
        "tuName": [
            "бК0.347.458-02ТУ",
            "П0.070.052"
        ],
        "manufacturerName": [
            "АО «НЗПП ВОСТОК»"
        ]
    },
    {
        "ekbName": "ОСМ 1526ИР9 ММ",
        "tuName": [
            "АЕЯР.431200.139-02ТУ",
            "П0.070.052"
        ],
        "manufacturerName": [
            "АО «МИКРОН»"
        ]
    },
    {
        "ekbName": "ОСМ 1526ИР9 ЭП",
        "tuName": [
            "АЕЯР.431200.126-02ТУ",
            "П0.070.052"
        ],
        "manufacturerName": [
            "АО «ЭКСИТОН»"
        ]
    },
    {
        "ekbName": "ОСМ 1526КП1",
        "tuName": [
            "бК0.347.458-03ТУ",
            "П0.070.052"
        ],
        "manufacturerName": [
            "АО «НЗПП ВОСТОК»"
        ]
    },
    {
        "ekbName": "ОСМ 1526КП1 ММ",
        "tuName": [
            "АЕЯР.431200.139-03ТУ",
            "П0.070.052"
        ],
        "manufacturerName": [
            "АО «МИКРОН»"
        ]
    },
    {
        "ekbName": "ОСМ 1526КП1 ЭП",
        "tuName": [
            "АЕЯР.431200.126-03ТУ",
            "П0.070.052"
        ],
        "manufacturerName": [
            "АО «ЭКСИТОН»"
        ]
    },
    {
        "ekbName": "ОСМ 1526КП2",
        "tuName": [
            "бК0.347.458-03ТУ",
            "П0.070.052"
        ],
        "manufacturerName": [
            "АО «НЗПП ВОСТОК»"
        ]
    },
    {
        "ekbName": "ОСМ 1526КП2 ММ",
        "tuName": [
            "АЕЯР.431200.139-03ТУ",
            "П0.070.052"
        ],
        "manufacturerName": [
            "АО «МИКРОН»"
        ]
    },
    {
        "ekbName": "ОСМ 1526КП2 ЭП",
        "tuName": [
            "АЕЯР.431200.126-03ТУ",
            "П0.070.052"
        ],
        "manufacturerName": [
            "АО «ЭКСИТОН»"
        ]
    },
    {
        "ekbName": "ОСМ 1526КТ3",
        "tuName": [
            "бК0.347.458-04ТУ",
            "П0.070.052"
        ],
        "manufacturerName": [
            "АО «ЭКСИТОН»"
        ]
    },
    {
        "ekbName": "ОСМ 1526КТ3 ММ",
        "tuName": [
            "АЕЯР.431200.139-04ТУ",
            "П0.070.052"
        ],
        "manufacturerName": [
            "АО «МИКРОН»"
        ]
    },
    {
        "ekbName": "ОСМ 1526ЛА10",
        "tuName": [
            "бК0.347.458-05ТУ",
            "П0.070.052"
        ],
        "manufacturerName": [
            "АО «НЗПП ВОСТОК»"
        ]
    },
    {
        "ekbName": "ОСМ 1526ЛА10 ММ",
        "tuName": [
            "АЕЯР.431200.139-05ТУ",
            "П0.070.052"
        ],
        "manufacturerName": [
            "АО «МИКРОН»"
        ]
    },
    {
        "ekbName": "ОСМ 1526ЛА10 ЭП",
        "tuName": [
            "АЕЯР.431200.126-07ТУ",
            "П0.070.052"
        ],
        "manufacturerName": [
            "АО «ЭКСИТОН»"
        ]
    },
    {
        "ekbName": "ОСМ 1526ЛА7",
        "tuName": [
            "бК0.347.458-01ТУ",
            "П0.070.052"
        ],
        "manufacturerName": [
            "АО «НЗПП ВОСТОК»"
        ]
    },
    {
        "ekbName": "ОСМ 1526ЛА7 ММ",
        "tuName": [
            "АЕЯР.431200.139-01ТУ",
            "П0.070.052"
        ],
        "manufacturerName": [
            "АО «МИКРОН»"
        ]
    },
    {
        "ekbName": "ОСМ 1526ЛА7 ЭП",
        "tuName": [
            "АЕЯР.431200.126-01ТУ",
            "П0.070.052"
        ],
        "manufacturerName": [
            "АО «ЭКСИТОН»"
        ]
    },
    {
        "ekbName": "ОСМ 1526ЛА8",
        "tuName": [
            "бК0.347.458-01ТУ",
            "П0.070.052"
        ],
        "manufacturerName": [
            "АО «НЗПП ВОСТОК»"
        ]
    },
    {
        "ekbName": "ОСМ 1526ЛА8 ММ",
        "tuName": [
            "АЕЯР.431200.139-01ТУ",
            "П0.070.052"
        ],
        "manufacturerName": [
            "АО «МИКРОН»"
        ]
    },
    {
        "ekbName": "ОСМ 1526ЛА8 ЭП",
        "tuName": [
            "АЕЯР.431200.126-01ТУ",
            "П0.070.052"
        ],
        "manufacturerName": [
            "АО «ЭКСИТОН»"
        ]
    },
    {
        "ekbName": "ОСМ 1526ЛА9",
        "tuName": [
            "бК0.347.458-07ТУ",
            "П0.070.052"
        ],
        "manufacturerName": [
            "АО «ЭКСИТОН»"
        ]
    },
    {
        "ekbName": "ОСМ 1526ЛА9 ММ",
        "tuName": [
            "АЕЯР.431200.139-07ТУ",
            "П0.070.052"
        ],
        "manufacturerName": [
            "АО «МИКРОН»"
        ]
    },
    {
        "ekbName": "ОСМ 1526ЛЕ10",
        "tuName": [
            "бК0.347.458-07ТУ",
            "П0.070.052"
        ],
        "manufacturerName": [
            "АО «ЭКСИТОН»"
        ]
    },
    {
        "ekbName": "ОСМ 1526ЛЕ10 ММ",
        "tuName": [
            "АЕЯР.431200.139-07ТУ",
            "П0.070.052"
        ],
        "manufacturerName": [
            "АО «МИКРОН»"
        ]
    },
    {
        "ekbName": "ОСМ 1526ЛЕ5",
        "tuName": [
            "бК0.347.458-15ТУ",
            "П0.070.052"
        ],
        "manufacturerName": [
            "АО «ЭКСИТОН»"
        ]
    },
    {
        "ekbName": "ОСМ 1526ЛЕ5 ММ",
        "tuName": [
            "АЕЯР.431200.139-15ТУ",
            "П0.070.052"
        ],
        "manufacturerName": [
            "АО «МИКРОН»"
        ]
    },
    {
        "ekbName": "ОСМ 1526ЛЕ6",
        "tuName": [
            "бК0.347.458-15ТУ",
            "П0.070.052"
        ],
        "manufacturerName": [
            "АО «ЭКСИТОН»"
        ]
    },
    {
        "ekbName": "ОСМ 1526ЛЕ6 ММ",
        "tuName": [
            "АЕЯР.431200.139-15ТУ",
            "П0.070.052"
        ],
        "manufacturerName": [
            "АО «МИКРОН»"
        ]
    },
    {
        "ekbName": "ОСМ 1526ЛН1",
        "tuName": [
            "бК0.347.458-13ТУ",
            "П0.070.052"
        ],
        "manufacturerName": [
            "АО «ЭКСИТОН»"
        ]
    },
    {
        "ekbName": "ОСМ 1526ЛН1 ММ",
        "tuName": [
            "АЕЯР.431200.139-13ТУ",
            "П0.070.052"
        ],
        "manufacturerName": [
            "АО «МИКРОН»"
        ]
    },
    {
        "ekbName": "ОСМ 1526ЛН2",
        "tuName": [
            "бК0.347.458-01ТУ",
            "П0.070.052"
        ],
        "manufacturerName": [
            "АО «НЗПП ВОСТОК»"
        ]
    },
    {
        "ekbName": "ОСМ 1526ЛН2 ММ",
        "tuName": [
            "АЕЯР.431200.139-01ТУ",
            "П0.070.052"
        ],
        "manufacturerName": [
            "АО «МИКРОН»"
        ]
    },
    {
        "ekbName": "ОСМ 1526ЛН2 ЭП",
        "tuName": [
            "АЕЯР.431200.126-01ТУ",
            "П0.070.052"
        ],
        "manufacturerName": [
            "АО «ЭКСИТОН»"
        ]
    },
    {
        "ekbName": "ОСМ 1526ЛП13",
        "tuName": [
            "бК0.347.458-01ТУ",
            "П0.070.052"
        ],
        "manufacturerName": [
            "АО «НЗПП ВОСТОК»"
        ]
    },
    {
        "ekbName": "ОСМ 1526ЛП13 ММ",
        "tuName": [
            "АЕЯР.431200.139-01ТУ",
            "П0.070.052"
        ],
        "manufacturerName": [
            "АО «МИКРОН»"
        ]
    },
    {
        "ekbName": "ОСМ 1526ЛП13 ЭП",
        "tuName": [
            "АЕЯР.431200.126-01ТУ",
            "П0.070.052"
        ],
        "manufacturerName": [
            "АО «ЭКСИТОН»"
        ]
    },
    {
        "ekbName": "ОСМ 1526ЛП2",
        "tuName": [
            "бК0.347.458-15ТУ",
            "П0.070.052"
        ],
        "manufacturerName": [
            "АО «ЭКСИТОН»"
        ]
    },
    {
        "ekbName": "ОСМ 1526ЛП2 ММ",
        "tuName": [
            "АЕЯР.431200.139-15ТУ",
            "П0.070.052"
        ],
        "manufacturerName": [
            "АО «МИКРОН»"
        ]
    },
    {
        "ekbName": "ОСМ 1526ЛС2",
        "tuName": [
            "бК0.347.458-11ТУ",
            "П0.070.052"
        ],
        "manufacturerName": [
            "АО «ЭКСИТОН»"
        ]
    },
    {
        "ekbName": "ОСМ 1526ЛС2 ММ",
        "tuName": [
            "АЕЯР.431200.139-11ТУ",
            "П0.070.052"
        ],
        "manufacturerName": [
            "АО «МИКРОН»"
        ]
    },
    {
        "ekbName": "ОСМ 1526ПР1",
        "tuName": [
            "бК0.347.458-05ТУ",
            "П0.070.052"
        ],
        "manufacturerName": [
            "АО «НЗПП ВОСТОК»"
        ]
    },
    {
        "ekbName": "ОСМ 1526ПР1 ЭП",
        "tuName": [
            "АЕЯР.431200.126-10ТУ",
            "П0.070.052"
        ],
        "manufacturerName": [
            "АО «ЭКСИТОН»"
        ]
    },
    {
        "ekbName": "ОСМ 1526ПУ4",
        "tuName": [
            "бК0.347.458-11ТУ",
            "П0.070.052"
        ],
        "manufacturerName": [
            "АО «ЭКСИТОН»"
        ]
    },
    {
        "ekbName": "ОСМ 1526ПУ4 ММ",
        "tuName": [
            "АЕЯР.431200.139-11ТУ",
            "П0.070.052"
        ],
        "manufacturerName": [
            "АО «МИКРОН»"
        ]
    },
    {
        "ekbName": "ОСМ 1526ПУ6",
        "tuName": [
            "бК0.347.458-05ТУ",
            "П0.070.052"
        ],
        "manufacturerName": [
            "АО «НЗПП ВОСТОК»"
        ]
    },
    {
        "ekbName": "ОСМ 1526ПУ6 ММ",
        "tuName": [
            "АЕЯР.431200.139-05ТУ",
            "П0.070.052"
        ],
        "manufacturerName": [
            "АО «МИКРОН»"
        ]
    },
    {
        "ekbName": "ОСМ 1526ПУ6 ЭП",
        "tuName": [
            "АЕЯР.431200.126-07ТУ",
            "П0.070.052"
        ],
        "manufacturerName": [
            "АО «ЭКСИТОН»"
        ]
    },
    {
        "ekbName": "ОСМ 1526ПУ7",
        "tuName": [
            "бК0.347.458-05ТУ",
            "П0.070.052"
        ],
        "manufacturerName": [
            "АО «НЗПП ВОСТОК»"
        ]
    },
    {
        "ekbName": "ОСМ 1526ПУ7 ММ",
        "tuName": [
            "АЕЯР.431200.139-05ТУ",
            "П0.070.052"
        ],
        "manufacturerName": [
            "АО «МИКРОН»"
        ]
    },
    {
        "ekbName": "ОСМ 1526ПУ7 ЭП",
        "tuName": [
            "АЕЯР.431200.126-08ТУ",
            "П0.070.052"
        ],
        "manufacturerName": [
            "АО «ЭКСИТОН»"
        ]
    },
    {
        "ekbName": "ОСМ 1526ПУ8",
        "tuName": [
            "бК0.347.458-05ТУ",
            "П0.070.052"
        ],
        "manufacturerName": [
            "АО «НЗПП ВОСТОК»"
        ]
    },
    {
        "ekbName": "ОСМ 1526ПУ8 ММ",
        "tuName": [
            "АЕЯР.431200.139-05ТУ",
            "П0.070.052"
        ],
        "manufacturerName": [
            "АО «МИКРОН»"
        ]
    },
    {
        "ekbName": "ОСМ 1526ПУ8 ЭП",
        "tuName": [
            "АЕЯР.431200.126-08ТУ",
            "П0.070.052"
        ],
        "manufacturerName": [
            "АО «ЭКСИТОН»"
        ]
    },
    {
        "ekbName": "ОСМ 1526ПУ91",
        "tuName": [
            "АЕЯР.431200.126-14ТУ",
            "П0.070.052"
        ],
        "manufacturerName": [
            "АО «ЭКСИТОН»"
        ]
    },
    {
        "ekbName": "ОСМ 1526СА1",
        "tuName": [
            "бК0.347.458-06ТУ",
            "П0.070.052"
        ],
        "manufacturerName": [
            "АО «ЭКСИТОН»"
        ]
    },
    {
        "ekbName": "ОСМ 1526ТВ1",
        "tuName": [
            "бК0.347.458-16ТУ",
            "П0.070.052"
        ],
        "manufacturerName": [
            "АО «ЭКСИТОН»"
        ]
    },
    {
        "ekbName": "ОСМ 1526ТВ1 ММ",
        "tuName": [
            "АЕЯР.431200.139-16ТУ",
            "П0.070.052"
        ],
        "manufacturerName": [
            "АО «МИКРОН»"
        ]
    },
    {
        "ekbName": "ОСМ 1526ТЛ1",
        "tuName": [
            "бК0.347.458-22ТУ",
            "П0.070.052"
        ],
        "manufacturerName": [
            "АО «ЭКСИТОН»"
        ]
    },
    {
        "ekbName": "ОСМ 1526ТЛ1 ММ",
        "tuName": [
            "АЕЯР.431200.139-22ТУ",
            "П0.070.052"
        ],
        "manufacturerName": [
            "АО «МИКРОН»"
        ]
    },
    {
        "ekbName": "ОСМ 1526ТМ2",
        "tuName": [
            "бК0.347.458-02ТУ",
            "П0.070.052"
        ],
        "manufacturerName": [
            "АО «НЗПП ВОСТОК»"
        ]
    },
    {
        "ekbName": "ОСМ 1526ТМ2 ММ",
        "tuName": [
            "АЕЯР.431200.139-02ТУ",
            "П0.070.052"
        ],
        "manufacturerName": [
            "АО «МИКРОН»"
        ]
    },
    {
        "ekbName": "ОСМ 1526ТМ2 ЭП",
        "tuName": [
            "АЕЯР.431200.126-02ТУ",
            "П0.070.052"
        ],
        "manufacturerName": [
            "АО «ЭКСИТОН»"
        ]
    },
    {
        "ekbName": "ОСМ 1526ТМ3",
        "tuName": [
            "бК0.347.458-12ТУ",
            "П0.070.052"
        ],
        "manufacturerName": [
            "АО «ЭКСИТОН»"
        ]
    },
    {
        "ekbName": "ОСМ 1526ТМ3 ММ",
        "tuName": [
            "АЕЯР.431200.139-12ТУ",
            "П0.070.052"
        ],
        "manufacturerName": [
            "АО «МИКРОН»"
        ]
    },
    {
        "ekbName": "ОСМ 1526ТР2",
        "tuName": [
            "бК0.347.458-12ТУ",
            "П0.070.052"
        ],
        "manufacturerName": [
            "АО «ЭКСИТОН»"
        ]
    },
    {
        "ekbName": "ОСМ 1526ТР2 ММ",
        "tuName": [
            "АЕЯР.431200.139-12ТУ",
            "П0.070.052"
        ],
        "manufacturerName": [
            "АО «МИКРОН»"
        ]
    }
]