[
    {
        "ekbName": "1664РУ1Н4",
        "tuName": [
            "ЮКСУ.431223.004ТУ"
        ],
        "manufacturerName": [
            "Порядок изготовления и поставок указанных изделий в 2023 году согласовывается с предприятием-калькодержателем указанных микросхем"
        ]
    },
    {
        "ekbName": "1664РУ1Т",
        "tuName": [
            "ЮКСУ.431223.004ТУ"
        ],
        "manufacturerName": [
            "Порядок изготовления и поставок указанных изделий в 2023 году согласовывается с предприятием-калькодержателем указанных микросхем"
        ]
    },
    {
        "ekbName": "1664РУ2Т",
        "tuName": [
            "ЮКСУ.431223.004ТУ"
        ],
        "manufacturerName": [
            "Порядок изготовления и поставок указанных изделий в 2023 году согласовывается с предприятием-калькодержателем указанных микросхем"
        ]
    },
    {
        "ekbName": "1664РУ3Т",
        "tuName": [
            "ЮКСУ.431223.004ТУ"
        ],
        "manufacturerName": [
            "Порядок изготовления и поставок указанных изделий в 2023 году согласовывается с предприятием-калькодержателем указанных микросхем"
        ]
    }
]