[
    {
        "Name": "ИЖЦ2-5/7",
        "Parameters": {
            "877": [
                "0.9"
            ],
            "878": [
                "30"
            ],
            "879": [
                "150"
            ],
            "null": [
                "на отражение"
            ],
            "880": [
                "12 - 25"
            ],
            "881": [
                "+50"
            ],
            "882": [
                "-10"
            ]
        }
    },
    {
        "Name": "ИЖЦ17-4/7",
        "Parameters": {
            "877": [
                "0.9"
            ],
            "878": [
                "100"
            ],
            "879": [
                "120"
            ],
            "null": [
                "на просвет"
            ],
            "880": [
                "8"
            ],
            "881": [
                "+55"
            ],
            "882": [
                "-10"
            ]
        }
    },
    {
        "Name": "ИЖЦ23-6/8 О",
        "Parameters": {
            "877": [
                "≥0.83"
            ],
            "878": [
                "250"
            ],
            "879": [
                "250"
            ],
            "null": [
                "на отражение"
            ],
            "880": [
                "≤15"
            ],
            "881": [
                "+55"
            ],
            "882": [
                "0"
            ]
        }
    },
    {
        "Name": "ИЖЦ23-6/8 П",
        "Parameters": {
            "877": [
                "≥0.83"
            ],
            "878": [
                "250"
            ],
            "879": [
                "250"
            ],
            "null": [
                "на просвет"
            ],
            "880": [
                "≤15"
            ],
            "881": [
                "+55"
            ],
            "882": [
                "0"
            ]
        }
    },
    {
        "Name": "ИЖЦ23-6/8 ПО",
        "Parameters": {
            "877": [
                "≥0.83"
            ],
            "878": [
                "250"
            ],
            "879": [
                "250"
            ],
            "null": [
                "просветно – отражатель-ный"
            ],
            "880": [
                "≤15"
            ],
            "881": [
                "+55"
            ],
            "882": [
                "0"
            ]
        }
    },
    {
        "Name": "ИЖЦ24-6/7",
        "Parameters": {
            "877": [
                "0.9"
            ],
            "878": [
                "100"
            ],
            "879": [
                "120"
            ],
            "null": [
                "на просвет"
            ],
            "880": [
                "12"
            ],
            "881": [
                "+55"
            ],
            "882": [
                "-10"
            ]
        }
    }
]