[
    {
        "Name": "РИ50-17-31",
        "Parameters": {
            "1149": [
                "3.0"
            ],
            "1150": [
                "0.04(0.15)",
                " 0.08(0.45)",
                " 0.11(0.7)",
                " 0.15(1"
            ],
            "1145": [
                "22.3 + 1.0"
            ],
            "1146": [
                "-60 ÷ +70"
            ]
        }
    },
    {
        "Name": "РИ75-4-11",
        "Parameters": {
            "1149": [
                "5.0"
            ],
            "1150": [
                "0.12(0.06)",
                " 0.36(0.6"
            ],
            "1145": [
                "7.0 ±0.4"
            ],
            "1146": [
                "-60 ÷ +70"
            ]
        }
    },
    {
        "Name": "РИ75-4-12",
        "Parameters": {
            "1149": [
                "5.0"
            ],
            "1150": [
                "0.15(0.06)",
                " 0.52(0.6"
            ],
            "1145": [
                "7.0 ±0.4"
            ],
            "1146": [
                "-60 ÷ +85"
            ]
        }
    },
    {
        "Name": "РИ75-7-11",
        "Parameters": {
            "1149": [
                "8.0"
            ],
            "1150": [
                "0.08(0.06)",
                " 0.30(0.6"
            ],
            "1145": [
                "11.2 ±0.4"
            ],
            "1146": [
                "-60 ÷ +70"
            ]
        }
    }
]